pfla/__init__.py
pfla/annotate.py
pfla/cli.py
pfla/face_detect.py
pfla/img_prep.py
pfla/linear.py
pfla/logger.py
pfla/metrics.py
pfla/tests/__init__.py
pfla/tests/test_integration.py
pfla/tests/data/__init__.py
pfla-1.0.0.dist-info/LICENSE.txt
pfla-1.0.0.dist-info/METADATA
pfla-1.0.0.dist-info/WHEEL
pfla-1.0.0.dist-info/entry_points.txt
pfla-1.0.0.dist-info/top_level.txt
pfla-1.0.0.dist-info/RECORD
