Metadata-Version: 2.1
Name: pfla
Version: 1.0.0
Summary: Python facial landmarking and analysis
Home-page: https://github.com/maxrousseau/pfla
Author: Maxime Rousseau
Author-email: maximerousseau08@gmail.com
License: MIT
Project-URL: Contribution guidelines, https://github.com/maxrousseau/pfla/blob/master/contributing.md
Project-URL: Issue Tracker, https://github.com/maxrousseau/pfla/issues
Project-URL: Source Code, https://github.com/maxrousseau/pfla
Platform: UNKNOWN
Classifier: Programming Language :: Python :: 3.5
Classifier: Programming Language :: Python :: 3.6
Classifier: Programming Language :: Python :: 3.7
Classifier: Topic :: Scientific/Engineering :: Medical Science Apps.
Classifier: Topic :: Scientific/Engineering :: Image Recognition
